Metadata-Version: 2.1
Name: dotrc
Version: 0.1.1
Summary: Simple .rc file loading for your Python projects
Home-page: https://pypi.org/project/dotrc/
Author: Paul Holden
Author-email: pholden@stria.com
License: MIT
Project-URL: GitHub, https://github.com/paulholden2/dotrc
Keywords: dot rc config file
Platform: UNKNOWN
Classifier: Programming Language :: Python :: 2.7
Classifier: Programming Language :: Python :: 3.4
Classifier: Programming Language :: Python :: 3.5
Classifier: Programming Language :: Python :: 3.6
Classifier: License :: OSI Approved :: MIT License
